streamlit_timeline/__init__.py
streamlit_timeline/frontend/build/asset-manifest.json
streamlit_timeline/frontend/build/bootstrap.min.css
streamlit_timeline/frontend/build/index.html
streamlit_timeline/frontend/build/index_bk.html
streamlit_timeline/frontend/build/precache-manifest.a632b80b25b19a605a90dd282a0397aa.js
streamlit_timeline/frontend/build/service-worker.js
streamlit_timeline/frontend/build/static/css/2.ab85016c.chunk.css
streamlit_timeline/frontend/build/static/css/2.ab85016c.chunk.css.map
streamlit_timeline/frontend/build/static/css/styles.css
streamlit_timeline/frontend/build/static/js/2.fc3cfd4b.chunk.js
streamlit_timeline/frontend/build/static/js/2.fc3cfd4b.chunk.js.LICENSE.txt
streamlit_timeline/frontend/build/static/js/2.fc3cfd4b.chunk.js.map
streamlit_timeline/frontend/build/static/js/main.46d91172.chunk.js
streamlit_timeline/frontend/build/static/js/main.46d91172.chunk.js.map
streamlit_timeline/frontend/build/static/js/runtime-main.44d30fc2.js
streamlit_timeline/frontend/build/static/js/runtime-main.44d30fc2.js.map
streamlit_timeline/styles/background.css
streamlit_vis_timeline-0.3.0.dist-info/LICENSE
streamlit_vis_timeline-0.3.0.dist-info/METADATA
streamlit_vis_timeline-0.3.0.dist-info/WHEEL
streamlit_vis_timeline-0.3.0.dist-info/top_level.txt
streamlit_vis_timeline-0.3.0.dist-info/RECORD
